{
    "asset": {
        "format": "jpg",
        "id": "36828e7486a62449c40e938735c7ed9e",
        "name": "csm_Industrie_Alpinamed3_02_a94a4f21af.jpg",
        "path": "file:C:/Users/caile/Documents/GitHub/TrainYourOwnYOLO/Data/Source_Images/Training_Images/IndustrialTanks/csm_Industrie_Alpinamed3_02_a94a4f21af.jpg",
        "size": {
            "width": 619,
            "height": 600
        },
        "state": 2,
        "type": 1
    },
    "regions": [
        {
            "id": "d8j7fBMH8",
            "type": "RECTANGLE",
            "tags": [
                "industrial tanks"
            ],
            "boundingBox": {
                "height": 600,
                "width": 55.31633771929825,
                "left": 0,
                "top": 0
            },
            "points": [
                {
                    "x": 0,
                    "y": 0
                },
                {
                    "x": 55.31633771929825,
                    "y": 0
                },
                {
                    "x": 55.31633771929825,
                    "y": 600
                },
                {
                    "x": 0,
                    "y": 600
                }
            ]
        },
        {
            "id": "91h-PZvvO",
            "type": "RECTANGLE",
            "tags": [
                "industrial tanks"
            ],
            "boundingBox": {
                "height": 598.6425339366516,
                "width": 109.95394736842105,
                "left": 52.26206140350877,
                "top": 1.3574660633484164
            },
            "points": [
                {
                    "x": 52.26206140350877,
                    "y": 1.3574660633484164
                },
                {
                    "x": 162.2160087719298,
                    "y": 1.3574660633484164
                },
                {
                    "x": 162.2160087719298,
                    "y": 600
                },
                {
                    "x": 52.26206140350877,
                    "y": 600
                }
            ]
        },
        {
            "id": "w9VHBHWrh",
            "type": "RECTANGLE",
            "tags": [
                "industrial tanks"
            ],
            "boundingBox": {
                "height": 508.0316742081448,
                "width": 64.47916666666666,
                "left": 154.75,
                "top": 53.619909502262445
            },
            "points": [
                {
                    "x": 154.75,
                    "y": 53.619909502262445
                },
                {
                    "x": 219.22916666666666,
                    "y": 53.619909502262445
                },
                {
                    "x": 219.22916666666666,
                    "y": 561.6515837104073
                },
                {
                    "x": 154.75,
                    "y": 561.6515837104073
                }
            ]
        },
        {
            "id": "MQd7c0_4Q",
            "type": "RECTANGLE",
            "tags": [
                "industrial tanks"
            ],
            "boundingBox": {
                "height": 408.25791855203624,
                "width": 38.6875,
                "left": 215.83552631578945,
                "top": 106.90045248868779
            },
            "points": [
                {
                    "x": 215.83552631578945,
                    "y": 106.90045248868779
                },
                {
                    "x": 254.52302631578945,
                    "y": 106.90045248868779
                },
                {
                    "x": 254.52302631578945,
                    "y": 515.158371040724
                },
                {
                    "x": 215.83552631578945,
                    "y": 515.158371040724
                }
            ]
        },
        {
            "id": "CYF-C_YHT",
            "type": "RECTANGLE",
            "tags": [
                "industrial tanks"
            ],
            "boundingBox": {
                "height": 327.48868778280547,
                "width": 40.384320175438596,
                "left": 244.00274122807016,
                "top": 171.38009049773757
            },
            "points": [
                {
                    "x": 244.00274122807016,
                    "y": 171.38009049773757
                },
                {
                    "x": 284.38706140350877,
                    "y": 171.38009049773757
                },
                {
                    "x": 284.38706140350877,
                    "y": 498.868778280543
                },
                {
                    "x": 244.00274122807016,
                    "y": 498.868778280543
                }
            ]
        },
        {
            "id": "DdslYd5Wp",
            "type": "RECTANGLE",
            "tags": [
                "industrial tanks"
            ],
            "boundingBox": {
                "height": 373.3031674208145,
                "width": 150.33826754385964,
                "left": 290.4956140350877,
                "top": 157.8054298642534
            },
            "points": [
                {
                    "x": 290.4956140350877,
                    "y": 157.8054298642534
                },
                {
                    "x": 440.83388157894734,
                    "y": 157.8054298642534
                },
                {
                    "x": 440.83388157894734,
                    "y": 531.1085972850678
                },
                {
                    "x": 290.4956140350877,
                    "y": 531.1085972850678
                }
            ]
        },
        {
            "id": "WkKjPB1iC",
            "type": "RECTANGLE",
            "tags": [
                "industrial tanks"
            ],
            "boundingBox": {
                "height": 373.98190045248873,
                "width": 75.6781798245614,
                "left": 450.3360745614035,
                "top": 146.94570135746608
            },
            "points": [
                {
                    "x": 450.3360745614035,
                    "y": 146.94570135746608
                },
                {
                    "x": 526.0142543859649,
                    "y": 146.94570135746608
                },
                {
                    "x": 526.0142543859649,
                    "y": 520.9276018099548
                },
                {
                    "x": 450.3360745614035,
                    "y": 520.9276018099548
                }
            ]
        },
        {
            "id": "Ptq87oUfw",
            "type": "RECTANGLE",
            "tags": [
                "industrial tanks"
            ],
            "boundingBox": {
                "height": 565.7239819004525,
                "width": 65.83662280701755,
                "left": 515.8333333333333,
                "top": 5.769230769230769
            },
            "points": [
                {
                    "x": 515.8333333333333,
                    "y": 5.769230769230769
                },
                {
                    "x": 581.6699561403509,
                    "y": 5.769230769230769
                },
                {
                    "x": 581.6699561403509,
                    "y": 571.4932126696833
                },
                {
                    "x": 515.8333333333333,
                    "y": 571.4932126696833
                }
            ]
        },
        {
            "id": "h4c3Af47U",
            "type": "RECTANGLE",
            "tags": [
                "industrial tanks"
            ],
            "boundingBox": {
                "height": 600,
                "width": 48.18969298245614,
                "left": 570.8103070175439,
                "top": 0
            },
            "points": [
                {
                    "x": 570.8103070175439,
                    "y": 0
                },
                {
                    "x": 619,
                    "y": 0
                },
                {
                    "x": 619,
                    "y": 600
                },
                {
                    "x": 570.8103070175439,
                    "y": 600
                }
            ]
        }
    ],
    "version": "2.1.0"
}