{
    "asset": {
        "format": "png",
        "id": "5fafda68bcbc7dcb4a47ce510fb30622",
        "name": "how-to-prevent-metal-corrosion-image.png",
        "path": "file:C:/Users/caile/Documents/GitHub/TrainYourOwnYOLO/Data/Source_Images/Training_Images/Corrosion/how-to-prevent-metal-corrosion-image.png",
        "size": {
            "width": 1500,
            "height": 1500
        },
        "state": 2,
        "type": 1
    },
    "regions": [
        {
            "id": "iRg981ekJ",
            "type": "RECTANGLE",
            "tags": [
                "rust",
                "corrosion"
            ],
            "boundingBox": {
                "height": 279.9773755656108,
                "width": 1044.4004524886877,
                "left": 453.9027149321267,
                "top": 603.2239819004525
            },
            "points": [
                {
                    "x": 453.9027149321267,
                    "y": 603.2239819004525
                },
                {
                    "x": 1498.3031674208144,
                    "y": 603.2239819004525
                },
                {
                    "x": 1498.3031674208144,
                    "y": 883.2013574660633
                },
                {
                    "x": 453.9027149321267,
                    "y": 883.2013574660633
                }
            ]
        },
        {
            "id": "FPO5ZNwGT",
            "type": "RECTANGLE",
            "tags": [
                "rust"
            ],
            "boundingBox": {
                "height": 57.69230769230769,
                "width": 67.02488687782805,
                "left": 341.0633484162896,
                "top": 499.71719457013575
            },
            "points": [
                {
                    "x": 341.0633484162896,
                    "y": 499.71719457013575
                },
                {
                    "x": 408.0882352941176,
                    "y": 499.71719457013575
                },
                {
                    "x": 408.0882352941176,
                    "y": 557.4095022624434
                },
                {
                    "x": 341.0633484162896,
                    "y": 557.4095022624434
                }
            ]
        },
        {
            "id": "YWIgZC31q",
            "type": "RECTANGLE",
            "tags": [
                "rust"
            ],
            "boundingBox": {
                "height": 57.69230769230769,
                "width": 65.32805429864253,
                "left": 758.4841628959276,
                "top": 498.868778280543
            },
            "points": [
                {
                    "x": 758.4841628959276,
                    "y": 498.868778280543
                },
                {
                    "x": 823.8122171945702,
                    "y": 498.868778280543
                },
                {
                    "x": 823.8122171945702,
                    "y": 556.5610859728507
                },
                {
                    "x": 758.4841628959276,
                    "y": 556.5610859728507
                }
            ]
        },
        {
            "id": "t44Rbk1jj",
            "type": "RECTANGLE",
            "tags": [
                "rust"
            ],
            "boundingBox": {
                "height": 48.35972850678733,
                "width": 61.08597285067873,
                "left": 1236.1425339366515,
                "top": 494.62669683257917
            },
            "points": [
                {
                    "x": 1236.1425339366515,
                    "y": 494.62669683257917
                },
                {
                    "x": 1297.2285067873304,
                    "y": 494.62669683257917
                },
                {
                    "x": 1297.2285067873304,
                    "y": 542.9864253393665
                },
                {
                    "x": 1236.1425339366515,
                    "y": 542.9864253393665
                }
            ]
        },
        {
            "id": "ju8IHcLCs",
            "type": "RECTANGLE",
            "tags": [
                "rust"
            ],
            "boundingBox": {
                "height": 50.90497737556561,
                "width": 52.60180995475113,
                "left": 1257.3529411764705,
                "top": 995.1923076923076
            },
            "points": [
                {
                    "x": 1257.3529411764705,
                    "y": 995.1923076923076
                },
                {
                    "x": 1309.9547511312217,
                    "y": 995.1923076923076
                },
                {
                    "x": 1309.9547511312217,
                    "y": 1046.0972850678734
                },
                {
                    "x": 1257.3529411764705,
                    "y": 1046.0972850678734
                }
            ]
        }
    ],
    "version": "2.1.0"
}