{
    "asset": {
        "format": "jpeg",
        "id": "74b41a0f95e0a3c57ca308cc3734e010",
        "name": "image8_5.jpeg",
        "path": "file:C:/Users/caile/Documents/GitHub/TrainYourOwnYOLO/Data/Source_Images/Training_Images/Corrosion/image8_5.jpeg",
        "size": {
            "width": 104,
            "height": 104
        },
        "state": 2,
        "type": 1
    },
    "regions": [
        {
            "id": "Tz33yRqc9",
            "type": "RECTANGLE",
            "tags": [
                "rust"
            ],
            "boundingBox": {
                "height": 53.64705882352941,
                "width": 71.17647058823529,
                "left": 14.411764705882353,
                "top": 5.411764705882353
            },
            "points": [
                {
                    "x": 14.411764705882353,
                    "y": 5.411764705882353
                },
                {
                    "x": 85.58823529411765,
                    "y": 5.411764705882353
                },
                {
                    "x": 85.58823529411765,
                    "y": 59.05882352941176
                },
                {
                    "x": 14.411764705882353,
                    "y": 59.05882352941176
                }
            ]
        },
        {
            "id": "D01LJC7U5",
            "type": "RECTANGLE",
            "tags": [
                "rust"
            ],
            "boundingBox": {
                "height": 45.05882352941176,
                "width": 26.52941176470588,
                "left": 47.88235294117647,
                "top": 54.529411764705884
            },
            "points": [
                {
                    "x": 47.88235294117647,
                    "y": 54.529411764705884
                },
                {
                    "x": 74.41176470588235,
                    "y": 54.529411764705884
                },
                {
                    "x": 74.41176470588235,
                    "y": 99.58823529411765
                },
                {
                    "x": 47.88235294117647,
                    "y": 99.58823529411765
                }
            ]
        }
    ],
    "version": "2.1.0"
}