{
    "asset": {
        "format": "jpg",
        "id": "8774f559333c0d3cf3342a72abc3fa09",
        "name": "chain-566778_1920.jpg",
        "path": "file:C:/Users/caile/Documents/GitHub/TrainYourOwnYOLO/Data/Source_Images/Training_Images/Corrosion/chain-566778_1920.jpg",
        "size": {
            "width": 1920,
            "height": 1275
        },
        "state": 2,
        "type": 1
    },
    "regions": [
        {
            "id": "Wv9gDB-UA",
            "type": "RECTANGLE",
            "tags": [
                "rust"
            ],
            "boundingBox": {
                "height": 561.0745614035087,
                "width": 825.7864077669904,
                "left": 6.524271844660195,
                "top": 4.645524945175438
            },
            "points": [
                {
                    "x": 6.524271844660195,
                    "y": 4.645524945175438
                },
                {
                    "x": 832.3106796116505,
                    "y": 4.645524945175438
                },
                {
                    "x": 832.3106796116505,
                    "y": 565.7200863486842
                },
                {
                    "x": 6.524271844660195,
                    "y": 565.7200863486842
                }
            ]
        },
        {
            "id": "w4ZNtkCZF",
            "type": "RECTANGLE",
            "tags": [
                "rust"
            ],
            "boundingBox": {
                "height": 867.7083333333333,
                "width": 1067.1844660194174,
                "left": 449.24271844660194,
                "top": 198.50517406798244
            },
            "points": [
                {
                    "x": 449.24271844660194,
                    "y": 198.50517406798244
                },
                {
                    "x": 1516.4271844660195,
                    "y": 198.50517406798244
                },
                {
                    "x": 1516.4271844660195,
                    "y": 1066.2135074013158
                },
                {
                    "x": 449.24271844660194,
                    "y": 1066.2135074013158
                }
            ]
        },
        {
            "id": "joVBPetU4",
            "type": "RECTANGLE",
            "tags": [
                "rust"
            ],
            "boundingBox": {
                "height": 575.0548245614035,
                "width": 766.1359223300971,
                "left": 1145.4757281553398,
                "top": 695.2705249451755
            },
            "points": [
                {
                    "x": 1145.4757281553398,
                    "y": 695.2705249451755
                },
                {
                    "x": 1911.611650485437,
                    "y": 695.2705249451755
                },
                {
                    "x": 1911.611650485437,
                    "y": 1270.325349506579
                },
                {
                    "x": 1145.4757281553398,
                    "y": 1270.325349506579
                }
            ]
        }
    ],
    "version": "2.1.0"
}