{
    "asset": {
        "format": "jpg",
        "id": "c3130cfd32877212e85983718d3cd971",
        "name": "pic76.jpg",
        "path": "file:C:/Users/caile/Documents/GitHub/TrainYourOwnYOLO/Data/Source_Images/Training_Images/Corrosion/pic76.jpg",
        "size": {
            "width": 1063,
            "height": 1184
        },
        "state": 2,
        "type": 1
    },
    "regions": [
        {
            "id": "Awtu1WxPj",
            "type": "RECTANGLE",
            "tags": [
                "rust"
            ],
            "boundingBox": {
                "height": 766.1176470588234,
                "width": 522.7978589420655,
                "left": 245.44849063287154,
                "top": 18.751131221719454
            },
            "points": [
                {
                    "x": 245.44849063287154,
                    "y": 18.751131221719454
                },
                {
                    "x": 768.2463495749371,
                    "y": 18.751131221719454
                },
                {
                    "x": 768.2463495749371,
                    "y": 784.868778280543
                },
                {
                    "x": 245.44849063287154,
                    "y": 784.868778280543
                }
            ]
        },
        {
            "id": "t4BPLXeJT",
            "type": "RECTANGLE",
            "tags": [
                "rust"
            ],
            "boundingBox": {
                "height": 254.47963800904975,
                "width": 141.24244332493703,
                "left": 113.57758383186399,
                "top": 30.13574660633484
            },
            "points": [
                {
                    "x": 113.57758383186399,
                    "y": 30.13574660633484
                },
                {
                    "x": 254.82002715680102,
                    "y": 30.13574660633484
                },
                {
                    "x": 254.82002715680102,
                    "y": 284.6153846153846
                },
                {
                    "x": 113.57758383186399,
                    "y": 284.6153846153846
                }
            ]
        }
    ],
    "version": "2.1.0"
}