{
    "asset": {
        "format": "jpg",
        "id": "c551fe4713a4fff5029383d6b01870c8",
        "name": "Industrial_storage_tanks.jpg",
        "path": "file:C:/Users/caile/Documents/GitHub/TrainYourOwnYOLO/Data/Source_Images/Training_Images/IndustrialTanks/Industrial_storage_tanks.jpg",
        "size": {
            "width": 1809,
            "height": 1041
        },
        "state": 2,
        "type": 1
    },
    "regions": [
        {
            "id": "ZsDSEDTid",
            "type": "RECTANGLE",
            "tags": [
                "industrial tanks"
            ],
            "boundingBox": {
                "height": 383.00943396226415,
                "width": 160.43619909502263,
                "left": 137.51674208144797,
                "top": 499.1321860259434
            },
            "points": [
                {
                    "x": 137.51674208144797,
                    "y": 499.1321860259434
                },
                {
                    "x": 297.9529411764706,
                    "y": 499.1321860259434
                },
                {
                    "x": 297.9529411764706,
                    "y": 882.1416199882076
                },
                {
                    "x": 137.51674208144797,
                    "y": 882.1416199882076
                }
            ]
        },
        {
            "id": "LtOdiKrY_",
            "type": "RECTANGLE",
            "tags": [
                "industrial tanks"
            ],
            "boundingBox": {
                "height": 374.82547169811323,
                "width": 192.35972850678732,
                "left": 329.0579185520362,
                "top": 508.9529407429245
            },
            "points": [
                {
                    "x": 329.0579185520362,
                    "y": 508.9529407429245
                },
                {
                    "x": 521.4176470588235,
                    "y": 508.9529407429245
                },
                {
                    "x": 521.4176470588235,
                    "y": 883.7784124410377
                },
                {
                    "x": 329.0579185520362,
                    "y": 883.7784124410377
                }
            ]
        },
        {
            "id": "_2vQPPrLC",
            "type": "RECTANGLE",
            "tags": [
                "industrial tanks"
            ],
            "boundingBox": {
                "height": 555.691037735849,
                "width": 173.53303167420813,
                "left": 1139.4244343891403,
                "top": 291.25954451650944
            },
            "points": [
                {
                    "x": 1139.4244343891403,
                    "y": 291.25954451650944
                },
                {
                    "x": 1312.9574660633484,
                    "y": 291.25954451650944
                },
                {
                    "x": 1312.9574660633484,
                    "y": 846.9505822523585
                },
                {
                    "x": 1139.4244343891403,
                    "y": 846.9505822523585
                }
            ]
        },
        {
            "id": "XnUaLUkCc",
            "type": "RECTANGLE",
            "tags": [
                "industrial tanks"
            ],
            "boundingBox": {
                "height": 504.95047169811323,
                "width": 252.11402714932126,
                "left": 1387.445701357466,
                "top": 452.483601120283
            },
            "points": [
                {
                    "x": 1387.445701357466,
                    "y": 452.483601120283
                },
                {
                    "x": 1639.5597285067872,
                    "y": 452.483601120283
                },
                {
                    "x": 1639.5597285067872,
                    "y": 957.4340728183962
                },
                {
                    "x": 1387.445701357466,
                    "y": 957.4340728183962
                }
            ]
        },
        {
            "id": "MhFnO5IWW",
            "type": "RECTANGLE",
            "tags": [
                "industrial tanks"
            ],
            "boundingBox": {
                "height": 196.41509433962264,
                "width": 462.4819004524887,
                "left": 1343.243891402715,
                "top": 734.0119030070755
            },
            "points": [
                {
                    "x": 1343.243891402715,
                    "y": 734.0119030070755
                },
                {
                    "x": 1805.7257918552036,
                    "y": 734.0119030070755
                },
                {
                    "x": 1805.7257918552036,
                    "y": 930.4269973466982
                },
                {
                    "x": 1343.243891402715,
                    "y": 930.4269973466982
                }
            ]
        }
    ],
    "version": "2.1.0"
}